mcp_ckan_server.py
ckan_mcp_server-0.0.1.dist-info/licenses/LICENSE
ckan_mcp_server-0.0.1.dist-info/METADATA
ckan_mcp_server-0.0.1.dist-info/WHEEL
ckan_mcp_server-0.0.1.dist-info/top_level.txt
ckan_mcp_server-0.0.1.dist-info/RECORD
