Metadata-Version: 2.4
Name: ckan-mcp-server
Version: 0.0.1
Summary: A Model Context Protocol (MCP) server for the CKAN API that enables browsing and managing CKAN data portals through MCP-compatible clients.
Author-email: Ondics GmbH <info@ondics.de>
Project-URL: Homepage, https://github.com/ondics/ckan-mcp-server
Project-URL: Issues, https://github.com/ondics/ckan-mcp-server/issues
Project-URL: Disussions, https://github.com/ondics/ckan-mcp-server/discussions
Requires-Python: >=3.8
License-File: LICENSE
Dynamic: license-file
